iio.py
pylibiio-0.23.1.dist-info/METADATA
pylibiio-0.23.1.dist-info/WHEEL
pylibiio-0.23.1.dist-info/top_level.txt
pylibiio-0.23.1.dist-info/RECORD
