Metadata-Version: 2.1
Name: pylibiio
Version: 0.23.1
Summary: Library for interfacing with Linux IIO devices
Home-page: https://github.com/analogdevicesinc/libiio
Maintainer: Analog Devices, Inc
Maintainer-email: travis.collins@analog.com
License: UNKNOWN
Platform: UNKNOWN
Classifier: Programming Language :: Python :: 3
Classifier: License :: OSI Approved :: GNU Lesser General Public License v2 or later (LGPLv2+)
Classifier: Operating System :: OS Independent
